noseparallel/__init__.py
noseparallel/plugin.py
nose_parallel-0.4.0.dist-info/LICENSE
nose_parallel-0.4.0.dist-info/METADATA
nose_parallel-0.4.0.dist-info/WHEEL
nose_parallel-0.4.0.dist-info/entry_points.txt
nose_parallel-0.4.0.dist-info/top_level.txt
nose_parallel-0.4.0.dist-info/RECORD
