Metadata-Version: 2.1
Name: nose-parallel
Version: 0.4.0
Summary: A nosetests plugin to split test suites to run in parallel
Home-page: https://github.com/dlanger/nose-parallel
Author: Daniel Langer
Author-email: daniel@langer.me
License: UNKNOWN
Platform: UNKNOWN
Classifier: Intended Audience :: Developers
Classifier: License :: OSI Approved :: MIT License
Classifier: Natural Language :: English
Classifier: Operating System :: OS Independent
Classifier: Programming Language :: Python
Classifier: Topic :: Software Development :: Testing
Classifier: Environment :: Console
